Metadata-Version: 1.1
Name: ferris-k8s-cli
Version: 0.0.1
Summary: Wrapper for Kubernetes API for usage within Ferris Platform.
Home-page: https://github.com/Ferris-Labs/ferris-k8s-cli
Author: Balaji Bal
Author-email: bal@ballab.com
License: Apache2.0
Download-URL: https://github.com/Ferris-Labs/ferris-k8s-cli/archive/0.0.1.tar.gz
Platform: UNKNOWN
Classifier: Development Status :: 3 - Alpha
Classifier: Environment :: Console
Classifier: Intended Audience :: Developers
Classifier: License :: OSI Approved :: GNU General Public License v3 (GPLv3)
Classifier: Operating System :: OS Independent
Classifier: Programming Language :: Python :: 3.6
Classifier: Topic :: System :: Logging
Classifier: Topic :: Software Development :: Libraries :: Python Modules
